{"cameraMode":{"drawMode":0,"name":"Shaded","section":"Shading Mode"},"sceneLighting":false,"audioPlay":false,"sceneViewState":{"m_AlwaysRefresh":false,"showFog":true,"showSkybox":false,"showFlares":true,"showImageEffects":true,"showParticleSystems":true,"showVisualEffectGraphs":true,"m_FxEnabled":true},"in2DMode":false,"pivot":{"x":-0.6392960548400879,"y":0.1949268877506256,"z":0.0852494090795517},"rotation":{"x":0.19052565097808839,"y":0.6963362097740173,"z":-0.6624611020088196,"w":0.200125589966774},"size":0.7416536211967468,"orthographic":false}